Workbook
Name PCT_INSALUBRIDADE: HeadCount!$AF$9
Name PCT_PERICULOSIDADE: HeadCount!$AF$10
Name SALARIO_MINIMO: HeadCount!$AF$8
Name TOTAL_ENCARGOS_PCT: 'Parâmetros Encargos'!$D$14

Sheet Instruções
B2: Orçamento 2027 - Headcount · Template consolidado (base para protótipo)
B4: Este template consolida a estrutura discutida: base de headcount de agosto/2026 com hierarquia Gerente > Diretor > VP, cálculo automático de Triênio/Anuênio, campos de Insalubridade/Periculosidade/Gratificação para revisão manual da área, e uma tabela de parâmetros de encargos e benefícios (exemplo, a validar).
B7: Aba | C7: O que contém | D7: Cor / convenção
B8: HeadCount | C8: Base de colaboradores + hierarquia (Gerente/Diretor/VP) + cálculo de Triênio e Anuênio | D8: Azul = editável pelo gestor · Preto = fórmula
B9: Parâmetros Encargos | C9: Tabela de encargos e benefícios (EXEMPLO — validar com Financeiro/RH) | D9: Amarelo = premissa a confirmar
B10: Promoções | C10: Intenção de promoção — busca pelo CÓD. DO FUNCIONÁRIO (não mais pelo nome) | D10: Verde = link para outra aba
B11: Adequações Salariais | C11: Intenção de ajuste salarial — mesma lógica de busca por código | D11: Verde = link para outra aba
B12: Aumento de Quadro | C12: Solicitação de novas posições, com cálculo de encargos pela tabela de parâmetros | D12: Azul = editável
B14: Pontos ainda em aberto (marcados como [A CONFIRMAR] neste arquivo): taxas reais de encargos/benefícios, regra de automação de Insalubridade/Periculosidade/Gratificação, e validação da hierarquia Gerente→Diretor→VP (ver aba HeadCount, linha de exemplo com observação).

Sheet Parâmetros Encargos
B2: Parâmetros de Encargos e Benefícios — EXEMPLO, validar com Financeiro/RH
B4: Parâmetro | C4: Base de cálculo | D4: % ou valor (exemplo) | E4: Observação
B5: INSS Patronal | C5: % sobre salário + adicionais | D5: 0.2 | E5: Alíquota padrão CLT — confirmar enquadramento (Simples/Lucro Real) [A CONFIRMAR]
B6: RAT/SAT (ajustado por FAP) | C6: % sobre salário + adicionais | D6: 0 | E6: Varia por CNAE e FAP da unidade — exemplo genérico [A CONFIRMAR]
B7: Sistema S (Sesc/Senac/Senai etc.) | C7: % sobre salário + adicionais | D7: 0.055 | E7: Depende do CNAE — exemplo [A CONFIRMAR]
B8: FGTS | C8: % sobre salário + adicionais | D8: 0.08 | E8: Padrão CLT
B9: 13º Salário (provisão mensal) | C9: % sobre salário + adicionais | D9: 0.0833 | E9: 1/12 avos
B10: INSS s/ 13º | C10: % sobre salário + adicionais | D10: 0.0496
B11: FGTS s/ 13º | C11: % sobre salário + adicionais | D11: 0.0156
B12: Férias + 1/3 (provisão mensal) | C12: % sobre salário + adicionais | D12: 0.1111 | E12: 1/12 avos + 1/3 sobre o 1/12
B13: Provisão Multa Rescisória | C13: % sobre salário + adicionais | D13: 0.04
D14: =SUM(D5:D13) -> 0.6346
B15: Todos os valores acima são EXEMPLO ilustrativo, não são os parâmetros reais da Vitru. Substituir pelos valores confirmados com Financeiro/RH antes de usar este template para decisão de orçamento.
B16: Célula D14 = soma de todos os encargos acima (% total sobre salário + adicionais). Esse total é usado em Promoções, Adequações Salariais e Aumento de Quadro via o nome definido TOTAL_ENCARGOS_PCT. Benefícios fixos por colaborador (VT, VR/VA, Saúde, Odontológico, Seguro de Vida) foram removidos do modelo de custo por decisão do time nesta versão.

Sheet HeadCount
B2: Orçamento 2027 - Headcount (base 08/2026)
B4: COLIGADA | C4: CÓD. UNIDADE | D4: UNIDADE | E4: CÓD. CC | F4: DESCRIÇÃO CC | G4: CÓD. FUNCIONÁRIO | H4: NOME DO FUNCIONÁRIO | I4: CARGO | J4: DATA DE ADMISSÃO | K4: TEMPO DE SERVIÇO (anos) | L4: SALÁRIO | M4: TRIÊNIO % | N4: TRIÊNIO (calc.) | O4: ANUÊNIO (pré-preenchido da folha) | P4: AJUDA DE CUSTO | Q4: ADIC. TITULAÇÃO | R4: INSALUBRIDADE? (1=sim / 0=não) | S4: PERICULOSIDADE? (1=sim / 0=não) | T4: GRATIFICAÇÃO (revisar área) | U4: OBSERVAÇÃO | V4: AJUSTES (INCLUSÃO/EXCLUSÃO) | W4: % Uniasselvi | X4: % Unicesumar | Y4: % Operações Próprias | Z4: % Operações Parceiras | AA4: GERENTE E-MAIL | AB4: DIRETOR E-MAIL | AC4: VP E-MAIL | AE4: PARÂMETROS TRIÊNIO | AG4: INSALUBRIDADE (calc. R$) | AH4: PERICULOSIDADE (calc. R$)
B5: 13 | C5: 1 | D5: CAMPUS EXEMPLO - MATRIZ | E5: 11010404087 | F5: EXEMPLO - SETOR ADMINISTRATIVO | G5: 13000000001 | H5: [Exemplo] Colaborador A | I5: ANALISTA ADMINISTRATIVO | J5: 43892 | K5: =DATEDIF(J5,TODAY(),"y") -> 6 | L5: 3200 | M5: =MIN(INT(DATEDIF($J5,$AF$7,"y")/3),$AF$6)*$AF$5 -> 0.06 | N5: =L5*M5 -> 192 | O5: 0 | P5: 0 | Q5: 0 | R5: 0 | S5: 0 | T5: 0 | AA5: gerente_exemplo_a@vitru.com.br | AB5: diretor_exemplo_a@vitru.com.br | AC5: vp_exemplo@vitru.com.br | AE5: % por Triênio (a cada 3 anos) | AF5: 0.03 | AG5: =IF(R5=1,SALARIO_MINIMO*PCT_INSALUBRIDADE,0) -> 0 | AH5: =IF(S5=1,L5*PCT_PERICULOSIDADE,0) -> 0
B6: 13 | C6: 1 | D6: CAMPUS EXEMPLO - MATRIZ | E6: 11010404087 | F6: EXEMPLO - SETOR ADMINISTRATIVO | G6: 13000000002 | H6: [Exemplo] Colaborador B | I6: AUXILIAR DE SERVIÇOS GERAIS | J6: 41105 | K6: =DATEDIF(J6,TODAY(),"y") -> 14 | L6: 1625.73 | M6: =MIN(INT(DATEDIF($J6,$AF$7,"y")/3),$AF$6)*$AF$5 -> 0.15 | N6: =L6*M6 -> 243.8595 | O6: 0 | P6: 0 | Q6: 0 | R6: 1 | S6: 0 | T6: 0 | U6: Insalubridade sinalizada p/ revisão da área | AA6: gerente_exemplo_a@vitru.com.br | AB6: diretor_exemplo_a@vitru.com.br | AC6: vp_exemplo@vitru.com.br | AE6: Teto (nº máx. de triênios) | AF6: 7 | AG6: =IF(R6=1,SALARIO_MINIMO*PCT_INSALUBRIDADE,0) -> 648.4 | AH6: =IF(S6=1,L6*PCT_PERICULOSIDADE,0) -> 0
B7: 13 | C7: 1 | D7: CAMPUS EXEMPLO - MATRIZ | E7: 21010404011 | F7: EXEMPLO - SEGURANÇA E PORTARIA | G7: 13000000003 | H7: [Exemplo] Colaborador C | I7: SUPERVISOR DE SEGURANÇA | J7: 43222 | K7: =DATEDIF(J7,TODAY(),"y") -> 8 | L7: 4401.73 | M7: =MIN(INT(DATEDIF($J7,$AF$7,"y")/3),$AF$6)*$AF$5 -> 0.09 | N7: =L7*M7 -> 396.1557 | O7: 0 | P7: 0 | Q7: 0 | R7: 0 | S7: 1 | T7: 0 | U7: Periculosidade sinalizada p/ revisão da área | AA7: gerente_exemplo_b@vitru.com.br | AB7: diretor_exemplo_a@vitru.com.br | AC7: vp_exemplo@vitru.com.br | AE7: Data-base (tempo de serviço) | AF7: 46752 | AG7: =IF(R7=1,SALARIO_MINIMO*PCT_INSALUBRIDADE,0) -> 0 | AH7: =IF(S7=1,L7*PCT_PERICULOSIDADE,0) -> 1320.519
AE8: Salário Mínimo (referência p/ Insalubridade) | AF8: 1621
B9: Triênio calculado com teto de 7 triênios, considerando data de admissão até 31/12/2027 (parâmetros em AA5:AB7). Anuênio NÃO é calculado — é um campo pré-preenchido com o valor já existente na folha de agosto/2026, levado como está para o orçado. Insalubridade = 40% do salário mínimo (se marcado 1); Periculosidade = 30% do salário base (se marcado 1) — parâmetros em AA8:AB10. Gratificação continua manual, sem regra de cálculo definida. | AE9: % Insalubridade sobre salário mínimo | AF9: 0.4
AE10: % Periculosidade sobre salário base | AF10: 0.3
B11: Nota de dados pessoais: os colaboradores acima são EXEMPLOS fictícios para ilustrar a estrutura. A base real de ~490 colaboradores permanece apenas no arquivo original de vocês — este template não reproduz remuneração individual real.
B13: Achado a validar: no arquivo de e-mails que vocês enviaram, um mesmo gerente aparecia vinculado a mais de um diretor em linhas diferentes. Antes de abrir o ciclo de orçamento, a área de Orçamento de Gente precisa revisar essa hierarquia (ver decisão de 'tela de conferência de estrutura').

Sheet Promoções
B2: Orçamento 2027 - Promoções
B4: Orientações: selecionar o CÓD. DO FUNCIONÁRIO (não o nome) — os demais campos vêm automaticamente da aba HeadCount. Informar cargo destino, salário destino, mês e justificativa.
B6: CÓD. FUNCIONÁRIO | C6: NOME (auto) | D6: UNIDADE (auto) | E6: CC (auto) | F6: CARGO ATUAL (auto) | G6: SALÁRIO ATUAL (auto) | H6: CARGO DESTINO | I6: SALÁRIO DESTINO | J6: % DE AJUSTE (calc.) | K6: ENCARGOS s/ AUMENTO (calc.) | L6: MÊS PREVISTO | M6: REFORMULAÇÃO DE ÁREA? | N6: JUSTIFICATIVA
B7: 13000000003 | C7: =IFERROR(INDEX(HeadCount!$H$5:$H$9999,MATCH($B7,HeadCount!$G$5:$G$9999,0)),"") -> [Exemplo] Colaborador C | D7: =IFERROR(INDEX(HeadCount!$D$5:$D$9999,MATCH($B7,HeadCount!$G$5:$G$9999,0)),"") -> CAMPUS EXEMPLO - MATRIZ | E7: =IFERROR(INDEX(HeadCount!$F$5:$F$9999,MATCH($B7,HeadCount!$G$5:$G$9999,0)),"") -> EXEMPLO - SEGURANÇA E PORTARIA | F7: =IFERROR(INDEX(HeadCount!$I$5:$I$9999,MATCH($B7,HeadCount!$G$5:$G$9999,0)),"") -> SUPERVISOR DE SEGURANÇA | G7: =IFERROR(INDEX(HeadCount!$L$5:$L$9999,MATCH($B7,HeadCount!$G$5:$G$9999,0)),"") -> 4401.73 | H7: COORDENADOR DE SEGURANÇA | I7: 5280 | J7: =IFERROR((I7/G7)-1,"") -> 0.19952837 | K7: =IFERROR((I7-G7)*TOTAL_ENCARGOS_PCT,"") -> 557.35014 | L7: Jan/2027 | M7: Não | N7: Mérito por desempenho no ciclo 2026
B9: Coluna 'Encargos s/ Aumento' calcula o custo adicional de encargos gerado só pelo aumento salarial, usando os parâmetros da aba 'Parâmetros Encargos' (INSS+RAT+Sistema S+FGTS+13º+Férias). Não inclui VT/VR/VA/Saúde, que não variam com o salário.

Sheet Adequações Salariais
B2: Orçamento 2027 - Adequações Salariais
B4: Orientações: selecionar o CÓD. DO FUNCIONÁRIO — os demais campos vêm automaticamente da aba HeadCount. Mesmo cargo, apenas ajuste de salário.
B6: CÓD. FUNCIONÁRIO | C6: NOME (auto) | D6: UNIDADE (auto) | E6: CC (auto) | F6: CARGO (auto) | G6: SALÁRIO ATUAL (auto) | H6: SALÁRIO DESTINO | I6: % DE AJUSTE (calc.) | J6: ENCARGOS s/ AUMENTO (calc.) | K6: MÊS PREVISTO | L6: REFORMULAÇÃO DE ÁREA? | M6: JUSTIFICATIVA
B7: 13000000003 | C7: =IFERROR(INDEX(HeadCount!$H$5:$H$9999,MATCH($B7,HeadCount!$G$5:$G$9999,0)),"") -> [Exemplo] Colaborador C | D7: =IFERROR(INDEX(HeadCount!$D$5:$D$9999,MATCH($B7,HeadCount!$G$5:$G$9999,0)),"") -> CAMPUS EXEMPLO - MATRIZ | E7: =IFERROR(INDEX(HeadCount!$F$5:$F$9999,MATCH($B7,HeadCount!$G$5:$G$9999,0)),"") -> EXEMPLO - SEGURANÇA E PORTARIA | F7: =IFERROR(INDEX(HeadCount!$I$5:$I$9999,MATCH($B7,HeadCount!$G$5:$G$9999,0)),"") -> SUPERVISOR DE SEGURANÇA | G7: =IFERROR(INDEX(HeadCount!$L$5:$L$9999,MATCH($B7,HeadCount!$G$5:$G$9999,0)),"") -> 4401.73 | H7: 4650 | I7: =IFERROR((H7/G7)-1,"") -> 0.056402823 | J7: =IFERROR((H7-G7)*TOTAL_ENCARGOS_PCT,"") -> 157.55214 | K7: Mar/2027 | L7: Não | M7: Equiparação salarial à média de mercado do cargo

Sheet Aumento de Quadro
B2: Orçamento 2027 - Aumento de Quadro
B4: Orientações: incluir solicitações de novas posições. O custo total (salário + encargos + benefícios) é calculado automaticamente pela tabela de parâmetros.
B6: COLIGADA | C6: UNIDADE | D6: CC | E6: DESCRIÇÃO CC | F6: CARGO/FUNÇÃO | G6: GERENTE RESPONSÁVEL (auto p/ e-mail) | H6: MÊS DE INÍCIO | I6: QUANTIDADE | J6: SALÁRIO PROPOSTO | K6: HAVERÁ INSALUB./PERICUL.? | L6: VALOR/% ADICIONAL | M6: CUSTO TOTAL MENSAL (calc.) | N6: VAGA AFIRMATIVA PCD? | O6: JUSTIFICATIVA
B7: 13 | C7: CAMPUS EXEMPLO - MATRIZ | D7: 11010404087 | E7: EXEMPLO - SETOR ADMINISTRATIVO | F7: ASSISTENTE ADMINISTRATIVO | G7: gerente_exemplo_a@vitru.com.br | H7: Fev/2027 | I7: 1 | J7: 2100 | K7: 0 | L7: 0 | M7: =(J7+L7)*(1+TOTAL_ENCARGOS_PCT) -> 3432.66 | N7: Não | O7: Substituição de posição enxugada em reestruturação de 2025
B9: Custo Total Mensal (calc.) = (Salário + Adicional) x (1 + % total de encargos da aba Parâmetros Encargos). Benefícios fixos por colaborador (VT, VR/VA, Saúde, Odontológico, Seguro de Vida) foram removidos do cálculo por decisão do time — não estão sendo projetados nesta versão.
